{
  "conditions": [
    {
      "type": "forge:and",
      "values": [
        {
          "flag": "frogs",
          "type": "quark:flag"
        },
        {
          "flag": "frog_brewing",
          "type": "quark:flag"
        }
      ]
    }
  ],
  "key": {
    "#": {
      "tag": "forge:nuggets/gold"
    },
    "L": {
      "item": "quark:frog_leg"
    }
  },
  "pattern": [
    "###",
    "#L#",
    "###"
  ],
  "result": {
    "item": "quark:golden_frog_leg"
  },
  "type": "minecraft:crafting_shaped"
}