{
  "pools": [
    {
      "conditions": [
        {
          "chance": 0.7,
          "condition": "random_chance_with_looting",
          "looting_multiplier": 0.1
        }
      ],
      "entries": [
        {
          "name": "alexsmobs:warped_muscle",
          "type": "item",
          "weight": 1
        }
      ],
      "name": "warped_mosco_1",
      "rolls": 1
    },
    {
      "entries": [
        {
          "functions": [
            {
              "count": {
                "max": 5,
                "min": 1
              },
              "function": "set_count"
            },
            {
              "count": {
                "max": 1,
                "min": 0
              },
              "function": "looting_enchant"
            }
          ],
          "name": "alexsmobs:hemolymph_sac",
          "type": "item",
          "weight": 1
        }
      ],
      "name": "warped_mosco_2",
      "rolls": 1
    }
  ]
}