{
  "altar_type": 2,
  "duration": 400,
  "effects": [
    "astralsorcery:built_in_effect_constellation_finish",
    "astralsorcery:built_in_effect_discovery_central_beam",
    "astralsorcery:altar_default_sparkle",
    "astralsorcery:built_in_effect_constellation_lines",
    "astralsorcery:built_in_effect_attunement_sparkle"
  ],
  "key": {
    "A": {
      "item": "astralsorcery:resonating_gem"
    },
    "B": {
      "tag": "forge:ingots/gold"
    },
    "C": {
      "tag": "forge:glass_panes"
    },
    "D": {
      "tag": "astralsorcery:stardust"
    },
    "E": {
      "item": "astralsorcery:glass_lens"
    },
    "F": {
      "canBeAttuned": true,
      "canBeCelestialCrystal": true,
      "hasToBeAttuned": false,
      "hasToBeCelestial": false,
      "type": "astralsorcery:crystal"
    },
    "G": {
      "item": "astralsorcery:infused_wood_engraved"
    },
    "H": {
      "item": "astralsorcery:marble_runed"
    }
  },
  "output": [
    {
      "count": 1,
      "item": "astralsorcery:prism"
    }
  ],
  "pattern": [
    "_A_A_",
    "BCDCB",
    "_EFE_",
    "GCDCG",
    "HH_HH"
  ],
  "recipe_class": "astralsorcery:constellation_base_average",
  "starlight": 1600,
  "type": "astralsorcery:altar"
}